ab/stat/__init__.py
ab/stat/export.py
ab/stat/util/Const.py
ab/stat/util/__init__.py
ab/stat/util/fetch_data.py
ab/stat/util/filter_raw_data.py
ab/stat/util/generate_plots.py
ab/stat/util/process_data.py
ab/stat/xls/__init__.py
ab/stat/xls/export_excel.py
ab/stat/xls/export_raw_excel.py
nn_stat-1.2.1.dist-info/licenses/LICENSE
nn_stat-1.2.1.dist-info/METADATA
nn_stat-1.2.1.dist-info/WHEEL
nn_stat-1.2.1.dist-info/top_level.txt
nn_stat-1.2.1.dist-info/RECORD
