Metadata-Version: 2.4
Name: nn-stat
Version: 1.2.1
Summary: Neural Network Performance Analysis
Home-page: https://ABrain.one
Author: ABrain One and contributors
Author-email: AI@ABrain.one
Classifier: Programming Language :: Python :: 3
Classifier: License :: OSI Approved :: MIT License
Classifier: Operating System :: OS Independent
Requires-Python: >=3.10
License-File: LICENSE
Requires-Dist: openpyxl
Requires-Dist: matplotlib
Requires-Dist: pandas
Requires-Dist: numpy
Requires-Dist: seaborn
Provides-Extra: dataset
Requires-Dist: nn-dataset; extra == "dataset"
Dynamic: author
Dynamic: author-email
Dynamic: classifier
Dynamic: description
Dynamic: description-content-type
Dynamic: home-page
Dynamic: license-file
Dynamic: provides-extra
Dynamic: requires-dist
Dynamic: requires-python
Dynamic: summary
